LICENSE
unimdgen/__init__.py
unimdgen/cli/__init__.py
unimdgen/cli/cli.py
unimdgen/cli/self_validation.py
unimdgen/config/__init__.py
unimdgen/config/api.py
unimdgen/config/constants.py
unimdgen/config/logging.py
unimdgen/config/paths.py
unimdgen/config/prompts.py
unimdgen/content/__init__.py
unimdgen/content/class_generator.py
unimdgen/content/module_page.py
unimdgen/content/notes_generator.py
unimdgen/content/revision_generator.py
unimdgen/content/sudoku_generator.py
unimdgen/content/summary_generator.py
unimdgen/main.py
unimdgen/processing/__init__.py
unimdgen/processing/data_parsing.py
unimdgen/processing/gpt_interaction.py
unimdgen/utilities/__init__.py
unimdgen/utilities/conversion_utilities.py
unimdgen/utilities/file_utilities.py
unimdgen/utilities/log_manager.py
unimdgen/utilities/text_utilities.py
templates/class_template.md
templates/module_flashcards.md
templates/module_practice_tests.md
templates/module_question_based_revision.md
templates/module_summary_notes.md
templates/module_summary_questions.md
templates/module_template.md
templates/note_template.md
unimdgen-0.6.1.dist-info/LICENSE
unimdgen-0.6.1.dist-info/METADATA
unimdgen-0.6.1.dist-info/WHEEL
unimdgen-0.6.1.dist-info/RECORD
