Metadata-Version: 2.1
Name: unimdgen
Version: 0.6.1
Summary: Generates markdown repositories for university mathematics modules based on raw material provided by the university.
License: MIT
Author: William F
Author-email: 110934475+unkokaeru@users.noreply.github.com
Requires-Python: >=3.12,<4.0
Classifier: License :: OSI Approved :: MIT License
Classifier: Programming Language :: Python :: 3
Classifier: Programming Language :: Python :: 3.12
Requires-Dist: Jinja2 (>=3.1.3,<4.0.0)
Requires-Dist: fitz (>=0.0.1.dev2,<0.0.2)
Requires-Dist: openai (>=1.23.2,<2.0.0)
